{
  "items": [
    {
      "id": "11",
      "category": "accessory",
      "name": "accessory",
      "price": 12000,
      "imagePath": "https://images.unsplash.com/photo-1608005109415-c397b60f6027?ixlib=rb-4.0.3&ixid=MnwxMjA3fDB8MHxwaG90by1wYWdlfHx8fGVufDB8fHx8&auto=format&fit=crop&w=1331&q=80"
    },
    {
      "id": "12",
      "category": "accessory",
      "name": "accessory",
      "price": 12000,
      "imagePath": "https://images.unsplash.com/photo-1608005109415-c397b60f6027?ixlib=rb-4.0.3&ixid=MnwxMjA3fDB8MHxwaG90by1wYWdlfHx8fGVufDB8fHx8&auto=format&fit=crop&w=1331&q=80"
    },
    {
      "id": "13",
      "category": "accessory",
      "name": "accessory",
      "price": 12000,
      "imagePath": "https://images.unsplash.com/photo-1608005109415-c397b60f6027?ixlib=rb-4.0.3&ixid=MnwxMjA3fDB8MHxwaG90by1wYWdlfHx8fGVufDB8fHx8&auto=format&fit=crop&w=1331&q=80"
    },
    {
      "id": "14",
      "category": "accessory",
      "name": "accessory",
      "price": 12000,
      "imagePath": "https://images.unsplash.com/photo-1608005109415-c397b60f6027?ixlib=rb-4.0.3&ixid=MnwxMjA3fDB8MHxwaG90by1wYWdlfHx8fGVufDB8fHx8&auto=format&fit=crop&w=1331&q=80"
    },
    {
      "id": "15",
      "category": "accessory",
      "name": "accessory",
      "price": 12000,
      "imagePath": "https://images.unsplash.com/photo-1608005109415-c397b60f6027?ixlib=rb-4.0.3&ixid=MnwxMjA3fDB8MHxwaG90by1wYWdlfHx8fGVufDB8fHx8&auto=format&fit=crop&w=1331&q=80"
    }
  ]
}
